CulturedLad/Spider.py
CulturedLad/__init__.py
CulturedLad-0.0.7.dist-info/METADATA
CulturedLad-0.0.7.dist-info/WHEEL
CulturedLad-0.0.7.dist-info/top_level.txt
CulturedLad-0.0.7.dist-info/RECORD
