Metadata-Version: 2.1
Name: CulturedLad
Version: 0.0.7
Summary: This is my module. Refer to README.md for its functions
Home-page: https://gitee.com/zhangxiao999
Author: CulturedLad
Author-email: 623178111@qq.com
